topsis_101703557/__init__.py
topsis_101703557/topsis_101703557.py
topsis_101703557-1.1.dist-info/LICENSE.txt
topsis_101703557-1.1.dist-info/METADATA
topsis_101703557-1.1.dist-info/WHEEL
topsis_101703557-1.1.dist-info/entry_points.txt
topsis_101703557-1.1.dist-info/top_level.txt
topsis_101703557-1.1.dist-info/RECORD
