Metadata-Version: 2.1
Name: topsis-101703557
Version: 1.1
Summary: A Python package to rank ML models/choices using topsis technique
Home-page: https://github.com/souravsharma6633/topsis-101703557
Author: Sourav Sharma
Author-email: souravsharma6633@gmail.com
License: MIT
Platform: UNKNOWN
Classifier: License :: OSI Approved :: MIT License
Classifier: Programming Language :: Python :: 3
Classifier: Programming Language :: Python :: 3.7
Requires-Dist: pandas
